secrit/__init__.py
secrit/main.py
secrit-0.0.5.dist-info/METADATA
secrit-0.0.5.dist-info/WHEEL
secrit-0.0.5.dist-info/licenses/LICENSE
secrit-0.0.5.dist-info/RECORD
