Metadata-Version: 2.1
Name: secrit
Version: 0.0.5
Summary: A simple library to interact with the 'pass' (password store https://www.passwordstore.org/) generated secrets
Project-URL: Homepage, https://github.com/hard-simp/secrit.py
Project-URL: Bug Tracker, https://github.com/hard-simp/secrit.py/issues
Author: Simpthy
License-File: LICENSE
Classifier: Intended Audience :: Developers
Classifier: Intended Audience :: End Users/Desktop
Classifier: Intended Audience :: System Administrators
Classifier: License :: OSI Approved :: MIT License
Classifier: Operating System :: MacOS :: MacOS X
Classifier: Operating System :: POSIX
Classifier: Programming Language :: Python :: 3
Requires-Python: >=3.7
